localambda/__init__.py
localambda/configuration.py
localambda/decorators.py
localambda/localogger.py
localambda/proxy.py
localambda/runner.py
localambda/serve.py
localambda/cli/__init__.py
localambda/cli/cli.py
mitm_scripts/__init__.py
mitm_scripts/reroute_traffic.py
localambda-0.0.1.dist-info/METADATA
localambda-0.0.1.dist-info/WHEEL
localambda-0.0.1.dist-info/entry_points.txt
localambda-0.0.1.dist-info/top_level.txt
localambda-0.0.1.dist-info/RECORD
